djpykafka/__init__.py
djpykafka/docs/__init__.py
djpykafka/docs/asyncapi.py
djpykafka/events/__init__.py
djpykafka/events/publish.py
djpykafka/events/subscribe.py
djpykafka/handlers/__init__.py
djpykafka/handlers/event_consumer.py
djpykafka/models/__init__.py
djpykafka/models/kafka_mixin.py
djpykafka/schemas/__init__.py
djpykafka/schemas/event.py
djpykafka/utils/__init__.py
djpykafka/utils/kafka.py
djpykafka-0.0.44.dist-info/LICENSE
djpykafka-0.0.44.dist-info/METADATA
djpykafka-0.0.44.dist-info/WHEEL
djpykafka-0.0.44.dist-info/top_level.txt
djpykafka-0.0.44.dist-info/RECORD
