Metadata-Version: 2.1
Name: djpykafka
Version: 0.0.44
Summary: Django + Pydantic + Kafka
Home-page: https://github.com/Voltane-EU/djpykafka
Author: Manuel Stingl
Author-email: info+opensource@voltane.eu
License: GNU LGPLv2.1
Classifier: Programming Language :: Python :: 3
Classifier: License :: OSI Approved :: GNU Lesser General Public License v2 or later (LGPLv2+)
Classifier: Operating System :: OS Independent
Classifier: Framework :: Django
Classifier: Topic :: Utilities
Requires-Python: >=3.6
License-File: LICENSE
Requires-Dist: djdantic >=0.0.6
Requires-Dist: kafka-python
Requires-Dist: djutils
